[
    {
        "created_time": "2018-06-29 23:04:16",
        "message": "[JTBC 뉴스룸] #다시보기▶https://t.co/M9LrkW7Qww ● '한반도 관통' 태풍 몰려온다…장마전선 만나 큰 피해 우려 ● '카잔 기적' 축구팀 귀국…일부 팬 '계란 투척' 돌출행동 ● '양… https://t.co/WtqKY14vku",
        "name": "JTBC_news",
        "num_likes": 21,
        "num_shares": 30,
        "post_id": "1012698266314534913"
    },
    {
        "created_time": "2018-06-29 23:00:23",
        "message": "[JTBC 뉴스룸] 성남시 \"아동수당, 현금 대신 지역화폐 지급\"…지역 경제를 살리는데 꼭 필요하다는 입장인데, 시민들 의견과는 대치. https://t.co/oWVrUQVo2A https://t.co/zinkxeBWYr",
        "name": "JTBC_news",
        "num_likes": 27,
        "num_shares": 41,
        "post_id": "1012697288303448065"
    },
    {
        "created_time": "2018-06-29 22:56:22",
        "message": "[JTBC 뉴스룸] 4대강, 수문의 50% 이상 연 곳은 \"강이 되살아난다\"…금강 상류와 미호천에서는 멸종위기 2급인 독수리 첫 관찰. https://t.co/KcTQxOTtky https://t.co/C8JnwqszDI",
        "name": "JTBC_news",
        "num_likes": 73,
        "num_shares": 154,
        "post_id": "1012696276893224960"
    },
    {
        "created_time": "2018-06-29 22:55:04",
        "message": "[JTBC 뉴스룸] 조양호 한진 회장, 이번에는 '사무장 약국' 20년 운영 의혹…1000억 원대 부당 이득 챙긴 정황 조사 중. https://t.co/TAKYob8mob https://t.co/fbwVSP9AD4",
        "name": "JTBC_news",
        "num_likes": 32,
        "num_shares": 46,
        "post_id": "1012695949741715456"
    },
    {
        "created_time": "2018-06-29 21:28:38",
        "message": "[JTBC 뉴스룸] '병역법 위반' 진행 중 재판 966건…검찰, 법리 검토 시작. 법원 역시 기존에 배당된 재판들의 진행을 일단은 중지할 듯. https://t.co/BrQLEAeHeS https://t.co/yxv3FBom62",
        "name": "JTBC_news",
        "num_likes": 9,
        "num_shares": 18,
        "post_id": "1012674201122103296"
    },
    {
        "created_time": "2018-06-29 20:34:35",
        "message": "[JTBC 뉴스룸] 양승태 사법부, 변협 회장 뒷조사 정황. 당시 '상고 법원' 도입 반대하자 대응문건 작성…\"내밀한 정보로 타격 가할 것\" https://t.co/ruqzL1lvXw https://t.co/qj61RWIWOG",
        "name": "JTBC_news",
        "num_likes": 24,
        "num_shares": 66,
        "post_id": "1012660599841361921"
    },
    {
        "created_time": "2018-06-29 20:17:28",
        "message": "[JTBC 뉴스룸] \"폼페이오, 다음 주 북한 방문\"…북·미 회담 이후 첫 고위급 접촉. 신고와 검증, 폐기로 이어지는 비핵화 일정표 논의 전망. https://t.co/j4IbaUpUHA https://t.co/NpyhOaqlJk",
        "name": "JTBC_news",
        "num_likes": 14,
        "num_shares": 16,
        "post_id": "1012656289992675329"
    },
    {
        "created_time": "2018-06-29 19:50:00",
        "message": "[JTBC 뉴스룸] JTBC 온에어 ▶https://t.co/M9LrkW7Qww  네이버ㆍ다음ㆍ네이트ㆍ유튜브를 통해 실시간 시청 가능합니다. https://t.co/lpzHqQW8YV",
        "name": "JTBC_news",
        "num_likes": 10,
        "num_shares": 2,
        "post_id": "1012649379897868288"
    },
    {
        "created_time": "2018-06-29 19:49:43",
        "message": "[JTBC 뉴스룸] 6월 29일 주요뉴스 ● \"폼페이오 내주 방북\" 후속협상 본격화 ● '양승태 대법' 변협 회장 '뒷조사' 정황 ● '병역법 위반' 진행 중 재판만도 1천건 ● 7호 태풍 북상…'한반도 관통' 우려",
        "name": "JTBC_news",
        "num_likes": 11,
        "num_shares": 8,
        "post_id": "1012649307344736256"
    },
    {
        "created_time": "2018-06-29 15:40:37",
        "message": "손흥민 \"우리 축구 희망 봤다\"…러시아 월드컵 한국대표팀 해단식. 신태용 감독 \"국민 환대 감사…성과 못 내 아쉬워\" (영상) https://t.co/ia5XUYnUjK https://t.co/0k3iJAMaPd",
        "name": "JTBC_news",
        "num_likes": 46,
        "num_shares": 63,
        "post_id": "1012586619663077376"
    },
    {
        "created_time": "2018-06-29 13:34:03",
        "message": "[속보] 국토부 \"진에어 문제 계속 검토…청문 등 추가절차 밟아야\"",
        "name": "JTBC_news",
        "num_likes": 33,
        "num_shares": 66,
        "post_id": "1012554765383823360"
    },
    {
        "created_time": "2018-06-29 11:45:39",
        "message": "'무너지고, 잠기고' 남부 비 피해 속출. 부산 '흰여울마을' 공사장 옹벽 무너지고, 울산 울주군에선 빗길 교통사고로 1명 숨지고 10명 다쳐. https://t.co/7ootgWpMWw https://t.co/uE0VvTwas0",
        "name": "JTBC_news",
        "num_likes": 14,
        "num_shares": 36,
        "post_id": "1012527486704410624"
    },
    {
        "created_time": "2018-06-29 11:14:41",
        "message": "주유소 빌린 뒤 '땅굴, 송유관 구멍' 만들어…5억원어치 기름 빨아 들여 훔친 일당 9명 검거. 송유관안전관리법 위반 혐의로 구속. https://t.co/ecowhjWqz3 https://t.co/xD4Hz9OY7u",
        "name": "JTBC_news",
        "num_likes": 16,
        "num_shares": 24,
        "post_id": "1012519693494599680"
    },
    {
        "created_time": "2018-06-29 10:42:21",
        "message": "[속보] 법원, '국정원 1억 뇌물' 최경환 징역 5년 선고",
        "name": "JTBC_news",
        "num_likes": 205,
        "num_shares": 406,
        "post_id": "1012511558172176384"
    },
    {
        "created_time": "2018-06-29 10:01:24",
        "message": "조양호, 15시간 조사 끝 오늘 새벽 귀가…상속에 500억원 내지 않는 혐의를 집중 추궁. 그러나 검찰 조사에서 대체로 혐의를 부인한 것으로 전해져. https://t.co/yxB9HUVUBU https://t.co/NbvW7OvTOk",
        "name": "JTBC_news",
        "num_likes": 16,
        "num_shares": 27,
        "post_id": "1012501252754661376"
    },
    {
        "created_time": "2018-06-29 09:58:07",
        "message": "#날씨 오늘도 곳곳 비·소나기...강원 영서·남부 내륙 최대 30mm. 주말내내 비가 쏟아지면서 많은 곳 최대 150mm 예상. 낮 기온은 서울 28도, 대전 30도, 대구 31도까지 오를 전망.… https://t.co/FMtwOOYA25",
        "name": "JTBC_news",
        "num_likes": 20,
        "num_shares": 43,
        "post_id": "1012500427210817537"
    },
    {
        "created_time": "2018-06-29 09:56:51",
        "message": "'태극전사 귀국'...오늘 오후 인천공항으로 귀국 예정. 주장 기성용 선수는 러시아에서 곧바로 영국으로 출국. https://t.co/Knz9gxo9sM https://t.co/3yFBMCNw71",
        "name": "JTBC_news",
        "num_likes": 21,
        "num_shares": 34,
        "post_id": "1012500105746759680"
    },
    {
        "created_time": "2018-06-29 09:55:53",
        "message": "서울 한공공원 야외수영장 오늘(29일)부터 차례로 개장. 오늘은 '뚝섬·광나루·잠실·잠원' 개장. https://t.co/kLyWVkCkJ9 https://t.co/z3CLG9YXZx",
        "name": "JTBC_news",
        "num_likes": 24,
        "num_shares": 49,
        "post_id": "1012499862821134336"
    },
    {
        "created_time": "2018-06-29 09:55:04",
        "message": "특검, 1호 소환자 드루킹 \"특검서 다 말하겠다\". 또 특검은 경찰 기록에 댓글조작 관여 정황이 파악된 드루킹 카페 '핵심 변호사' 2명도 추가 입건. https://t.co/LbJWieQ3w7 https://t.co/qT1Tfmwj3L",
        "name": "JTBC_news",
        "num_likes": 10,
        "num_shares": 15,
        "post_id": "1012499658642296833"
    },
    {
        "created_time": "2018-06-29 09:54:06",
        "message": "'장자연 성추행 사건' 목격자 인터뷰 \"검찰, 가해자 말만 들었다\". 소속사 동료였던 윤모 씨는 과거사위원회 재소사에도 적극 협조하겠다는 의지 밝혀. https://t.co/ozxIwd7EKt https://t.co/eVRae7GEJd",
        "name": "JTBC_news",
        "num_likes": 51,
        "num_shares": 138,
        "post_id": "1012499415821500416"
    },
    {
        "created_time": "2018-06-29 09:53:06",
        "message": "\"폼페이오, 다음주 북한 다시 방문\" 파이낸셜타임스 보도. 싱가포르 회담 이후 북·미간 첫 고위급 만남. 비핵화와 체제보장 '빅딜' 논의 본격화할 전망. https://t.co/zEOWWIyFHf https://t.co/j7HkwThJlW",
        "name": "JTBC_news",
        "num_likes": 19,
        "num_shares": 13,
        "post_id": "1012499162816864256"
    },
    {
        "created_time": "2018-06-29 06:45:15",
        "message": "6월 29일 JTBC 아침&amp; 예고 ●\"폼페이오 다음 주 북한 방문\" ●내년 말까지 대체복무제 도입 ●'장자연 성추행' 목격자 인터뷰 ●조양호 회장 조사…구속영장 검토 https://t.co/b2OlfztAj1",
        "name": "JTBC_news",
        "num_likes": 14,
        "num_shares": 20,
        "post_id": "1012451888812384256"
    },
    {
        "created_time": "2018-06-28 23:11:27",
        "message": "[JTBC 뉴스룸] #다시보기 ▶https://t.co/6laMsJLfR1  ● 헌재 '양심적 병역거부' 사실상 인정…대체복무 길 열린다 ● 특검 '소환 1호'는 드루킹…카페 '핵심' 두 변호사도 추가 입건… https://t.co/BGvpK7eFv1",
        "name": "JTBC_news",
        "num_likes": 23,
        "num_shares": 12,
        "post_id": "1012337685694898176"
    },
    {
        "created_time": "2018-06-28 23:11:08",
        "message": "[JTBC 뉴스룸] #팩트체크 #월드컵 #붉은악마 가 어제(27일) 독일전을 앞두고 FIFA로부터 응원 도구와 관련해 차별을 받았다는 보도가 나왔습니다. 그 논란을 팩트체크 팀에서 짚어봤습니다.… https://t.co/AO8pxH45Ju",
        "name": "JTBC_news",
        "num_likes": 17,
        "num_shares": 33,
        "post_id": "1012337606674112512"
    },
    {
        "created_time": "2018-06-28 23:06:40",
        "message": "[JTBC 뉴스룸] #앵커브리핑 기억하라 '15대 0' https://t.co/mq4kAjCJ0C 축구 때문에 환호하고 실망했을 모두를 위해 이쾌대의 글 '15대 0' 첫머리를 옮겨드립니다. 그리고 오늘의… https://t.co/qZyvfaYnLD",
        "name": "JTBC_news",
        "num_likes": 36,
        "num_shares": 23,
        "post_id": "1012336483464646656"
    },
    {
        "created_time": "2018-06-28 23:05:30",
        "message": "[JTBC 뉴스룸] #밀착카메라 12만 유해 아직 그곳에…'이름' 찾아주는 경건한 손길. 1951년, 치열한 전투가 벌어졌던 강원 홍천 '벙커고지'에서 유해발굴 한창 https://t.co/HgcZwi42Wc https://t.co/koYxRkLrZr",
        "name": "JTBC_news",
        "num_likes": 23,
        "num_shares": 44,
        "post_id": "1012336188772872192"
    },
    {
        "created_time": "2018-06-28 23:00:44",
        "message": "[JTBC 뉴스룸] \"아스팔트로 #미세먼지 잡는다\"… '광촉매'로 미세먼지 만드는 질소산화물 분해. 실내 실험실에선 42.8% 감소…강남대로 시험시공. 서울시, 올가을까지 효과를 검증한 뒤 내년 포장구역을… https://t.co/9mEensYPgo",
        "name": "JTBC_news",
        "num_likes": 39,
        "num_shares": 86,
        "post_id": "1012334990019850240"
    },
    {
        "created_time": "2018-06-28 22:50:04",
        "message": "[JTBC 뉴스룸] \"구급차 흔들린다\" 구급차 안에서 소방대원 또 폭행당해. 약발 안 듣는 대책…구급대원 폭행 3년간 564건, 이틀에 한 번꼴로 발생 https://t.co/MPD1oJWRB1 https://t.co/gzle1088fQ",
        "name": "JTBC_news",
        "num_likes": 70,
        "num_shares": 544,
        "post_id": "1012332304260141056"
    },
    {
        "created_time": "2018-06-28 22:43:30",
        "message": "[JTBC 뉴스룸] #인터뷰 고 장자연 씨의 동료이자 당시 장 씨에 대한 성추행을 수사기관에 진술했던 목격자 윤모 씨를 전화로 연결했습니다. \"당시 검찰이 자신을 거짓말쟁이로 몰아갔다\"며 장 씨에 대한 미안… https://t.co/SnKbylquoE",
        "name": "JTBC_news",
        "num_likes": 65,
        "num_shares": 107,
        "post_id": "1012330653214339076"
    },
    {
        "created_time": "2018-06-28 22:24:41",
        "message": "[JTBC 뉴스룸] '장자연 성추행' 사건을 맡았던 검찰, 당시 가해자로 지목된 조 씨의 변명과 번복에도 \"정치지망생이어서\" 수긍된다며 불기소 처분. 최근 재수사에서 당시 관계자들이 사건의 실체를 왜곡시키려… https://t.co/c3Prmsfa4w",
        "name": "JTBC_news",
        "num_likes": 98,
        "num_shares": 360,
        "post_id": "1012325917291499520"
    },
    {
        "created_time": "2018-06-28 22:13:15",
        "message": "[JTBC 뉴스룸] 조양호 회장, '상속세 탈루' 등 혐의로 검찰 출석. 부인과 두 딸에 이어 '죄송하다'는 말만 반복… 하지만 혐의를 인정하거나 사과한 적은 없어 https://t.co/sOluHSa68H https://t.co/1seDkMHwqx",
        "name": "JTBC_news",
        "num_likes": 11,
        "num_shares": 27,
        "post_id": "1012323038526730240"
    },
    {
        "created_time": "2018-06-28 22:05:10",
        "message": "[JTBC 뉴스룸] 국방부 \"최단기간 내에 대체복무 정책 내겠다\"…'복무기간 3년, 강도 높은 업무' 방안 등 검토. 현역병들이 상실감을 느끼지 않도록 하는 방법 고려 중… https://t.co/kzh021zyKl",
        "name": "JTBC_news",
        "num_likes": 25,
        "num_shares": 50,
        "post_id": "1012321005216280577"
    },
    {
        "created_time": "2018-06-28 21:56:24",
        "message": "[JTBC 뉴스룸] 충격의 '패장'에게 감독직 보장한 독일…\"신태용 유임은 어떻게 생각?\" 질문에 차범근, 짧은 침묵 후 밝힌 입장. #인터뷰 https://t.co/RIrugG7V9S https://t.co/CuuMahbjVo",
        "name": "JTBC_news",
        "num_likes": 32,
        "num_shares": 25,
        "post_id": "1012318800224518144"
    },
    {
        "created_time": "2018-06-28 21:50:42",
        "message": "[JTBC 뉴스룸] 태극전사, 1위 독일 '격침'…냉소와 조롱 딛고 마지막까지 힘껏 뛰어준 선수들. 독일전의 눈물은 더 애틋하게 전해져. https://t.co/KmtNRt7RfR https://t.co/XVQxIqJ3B9",
        "name": "JTBC_news",
        "num_likes": 82,
        "num_shares": 42,
        "post_id": "1012317363583139841"
    },
    {
        "created_time": "2018-06-28 19:49:16",
        "message": "[JTBC 뉴스룸] JTBC 온에어 ▶https://t.co/M9LrkW7Qww  네이버ㆍ다음ㆍ네이트ㆍ유튜브를 통해 실시간 시청 가능합니다. https://t.co/lpzHqQW8YV",
        "name": "JTBC_news",
        "num_likes": 6,
        "num_shares": 7,
        "post_id": "1012286805289287681"
    },
    {
        "created_time": "2018-06-28 19:48:59",
        "message": "[JTBC 뉴스룸] 6월 28일 주요뉴스 ● \"월드컵 역사상 가장 충격적 사건\" ● FIFA가 꼽은 '기적의 수문장' 조현우 ● 헌재 '양심적 병역거부' 사실상 인정 ● '장자연 성추행' 목격자…육성 증언 ● 상속세 탈루 혐의…조양호 회장 소환",
        "name": "JTBC_news",
        "num_likes": 23,
        "num_shares": 21,
        "post_id": "1012286734887936000"
    },
    {
        "created_time": "2018-06-28 15:12:16",
        "message": "부산·울산·경남 여당 단체장, 가덕도 신공항 재추진 의사. 여론의 공론화 과정이 필요한 상황에 '밀양 공항' 추진하던 한국당 소속 대구·경북 단체장과도 대립하며 정치적 대결 양상.… https://t.co/Uq60lOodTh",
        "name": "JTBC_news",
        "num_likes": 15,
        "num_shares": 30,
        "post_id": "1012217095134691328"
    },
    {
        "created_time": "2018-06-28 14:10:55",
        "message": "[속보] 헌재 \"'양심적 병역거부' 처벌조항 합헌\"",
        "name": "JTBC_news",
        "num_likes": 66,
        "num_shares": 520,
        "post_id": "1012201657973669888"
    },
    {
        "created_time": "2018-06-28 14:00:01",
        "message": "서울 노른자위 땅 공시가격, 시세의 30%...보유세 강북아파트 절반도 안 돼. 보유세 개편 앞두고 왜곡된 공시가격부터 바로 잡아야 한다는 지적. https://t.co/wxBJgQBbVI https://t.co/6kmea9pRcB",
        "name": "JTBC_news",
        "num_likes": 44,
        "num_shares": 57,
        "post_id": "1012198914882076673"
    },
    {
        "created_time": "2018-06-28 13:01:22",
        "message": "홍문종 의원, 교비 75억원 횡령 혐의에도 결국 불구속...체포동의안 제출했지만 국회가 부결. '방탄국회'로 인해 법의 형평성이 훼손된 것이라는 지적. https://t.co/Em4c9SmGck https://t.co/Re9Ojxwvbb",
        "name": "JTBC_news",
        "num_likes": 44,
        "num_shares": 157,
        "post_id": "1012184152832000000"
    },
    {
        "created_time": "2018-06-28 11:53:56",
        "message": "\"31년 전 KAL기 폭파 사건 진실 밝혀라\" 실종자 가족들, 전 씨가 사건을 조작했다고 주장하며 자택 앞에 모여 진상규명 요구. 7월 중 관련 주범 고소할 계획 밝혀.… https://t.co/UE1LIoIpuk",
        "name": "JTBC_news",
        "num_likes": 28,
        "num_shares": 62,
        "post_id": "1012167183084838913"
    },
    {
        "created_time": "2018-06-28 11:11:29",
        "message": "6만원이면 가짜 면허증 '뚝딱'...10대의 비극 된 '무면허 운전' 실태. 미성년자도 출생 연도만 조작하면, 하루 만에 위조 면허 발급 가능, 앱을 이용한 공유 차량도 손쉽게 대여.… https://t.co/eFSbNdYVko",
        "name": "JTBC_news",
        "num_likes": 22,
        "num_shares": 100,
        "post_id": "1012156503061479426"
    },
    {
        "created_time": "2018-06-28 10:47:02",
        "message": "[속보] 드루킹 특검, 드루킹 구치소 수용실 압수수색...첫 강제수사",
        "name": "JTBC_news",
        "num_likes": 31,
        "num_shares": 46,
        "post_id": "1012150350235619329"
    },
    {
        "created_time": "2018-06-28 09:53:06",
        "message": "#날씨 남부 장맛비·중부 소나기...경남·제주 50~100m, 많은 곳은 150m 이상 쏟아질 것으로 예상. 낮 기온은 서울 28도, 광주·대구 27도까지 오를 전망.… https://t.co/ZDlRCYxfZF",
        "name": "JTBC_news",
        "num_likes": 15,
        "num_shares": 90,
        "post_id": "1012136775555248128"
    },
    {
        "created_time": "2018-06-28 09:33:49",
        "message": "북한, 해마다 발행하던 '6·25 반미 우표' 발행 전면 보류. \"북·미 회담에 이은 또 하나의 데탕트 신호\" AP통신 보도 인용. https://t.co/kXGGILO2Im https://t.co/3RhbjKjRql",
        "name": "JTBC_news",
        "num_likes": 38,
        "num_shares": 79,
        "post_id": "1012131920614846464"
    },
    {
        "created_time": "2018-06-28 09:26:29",
        "message": "[속보] '횡령·배임 등 혐의' 조양호 한진그룹 회장 검찰 출석",
        "name": "JTBC_news",
        "num_likes": 32,
        "num_shares": 62,
        "post_id": "1012130078220697601"
    },
    {
        "created_time": "2018-06-28 09:23:20",
        "message": "유네스코 \"일본, 군함도 전체 역사 알려야\" 결정문 전체동의로 채택. 군함도 포함 근대산업시설을 국제사회에 이해시킬 수 있는 방안 마련 촉구. https://t.co/p35FsY0n1x https://t.co/daLWiWCfVU",
        "name": "JTBC_news",
        "num_likes": 124,
        "num_shares": 527,
        "post_id": "1012129284389945344"
    },
    {
        "created_time": "2018-06-28 09:22:44",
        "message": "볼턴 \"북한, 비핵화 빠르게 진행하길\" 다시 압박. 북·미간 협상 내용 의회 보고하는 '대북 정책 감독법' 발의. https://t.co/HI3aOLbnkn https://t.co/w9Gd34DCt9",
        "name": "JTBC_news",
        "num_likes": 18,
        "num_shares": 11,
        "post_id": "1012129134401634304"
    },
    {
        "created_time": "2018-06-28 09:21:45",
        "message": "김영권·손흥민 연속골…한국 대표팀, 독일에 2-0 완승 쾌거. 멕시코가 스웨덴에 0대 3 완패하면서 16강행은 무산. https://t.co/A13LWHRRzG https://t.co/pWPWreZqtP",
        "name": "JTBC_news",
        "num_likes": 55,
        "num_shares": 50,
        "post_id": "1012128885167673344"
    },
    {
        "created_time": "2018-06-28 06:48:22",
        "message": "6월 28일 JTBC 아침&amp; 예고 ●한국, 독일 2-0 격침…16강행 좌절 ●볼턴 \"북한 비핵화 빠르게 진행하길\" ●유네스코 \"일본, 군함도 역사 알려야\" ●삼성전자-애플 '특허 분쟁' 종지부 https://t.co/b2OlfztAj1",
        "name": "JTBC_news",
        "num_likes": 15,
        "num_shares": 13,
        "post_id": "1012090287416532992"
    },
    {
        "created_time": "2018-06-27 23:04:19",
        "message": "[JTBC 뉴스룸] #다시보기 ▶https://t.co/6laMsJLfR1  ● 판사 블랙리스트 재조사 직전 디가우징된 PC…'묘한 시점' ● 한미연합사령관 \"도발적 훈련만 중단…오랜 적과의 신뢰쌓기\" ●… https://t.co/rhzj1KUW5T",
        "name": "JTBC_news",
        "num_likes": 17,
        "num_shares": 12,
        "post_id": "1011973505179516928"
    },
    {
        "created_time": "2018-06-27 23:02:55",
        "message": "[JTBC 뉴스룸] #팩트체크 #사법농단의혹 의 중요한 증거가 될 수 있는 '디가우징', 주요 쟁점인 '복구 가능 여부'와 '증거인멸죄'에 대해 팩트체크 팀에서 짚어봤습니다.… https://t.co/qX7l4Hztnj",
        "name": "JTBC_news",
        "num_likes": 30,
        "num_shares": 29,
        "post_id": "1011973151276728320"
    },
    {
        "created_time": "2018-06-27 22:57:20",
        "message": "[JTBC 뉴스룸] #앵커브리핑 '도도새는 날지 않았다' https://t.co/izM6maHBtb 야당의 뒷자리에서는 때아닌 비유가 난무하는 중… 이제는 도도새의 교훈을 되새겨 봄직도 하지 않을까… 날개… https://t.co/7hwxw4IBNZ",
        "name": "JTBC_news",
        "num_likes": 30,
        "num_shares": 27,
        "post_id": "1011971747413819396"
    },
    {
        "created_time": "2018-06-27 22:56:38",
        "message": "[JTBC 뉴스룸] #밀착카메라 강원도 태백시 38번 국도변 따라 '시뻘건 물' 흘러내려. 폐광된 탄광 갱구에서 흘러나오는 중금속 성분의 갱내수로 인한 환경오염…주민들 '시름시름'… https://t.co/zTBbMJ1GCf",
        "name": "JTBC_news",
        "num_likes": 31,
        "num_shares": 99,
        "post_id": "1011971571202736128"
    },
    {
        "created_time": "2018-06-27 22:48:01",
        "message": "[JTBC 뉴스룸] 미 캘리포니아 북부 산불, 나흘째…주택 22채 전소·주민 수천 명 대피. 일대가 건조하고 바람이 강해 당국은 추가 피해 주시 중 https://t.co/lz52iPFV6a https://t.co/dBB3YEPbaP",
        "name": "JTBC_news",
        "num_likes": 18,
        "num_shares": 29,
        "post_id": "1011969401862512640"
    },
    {
        "created_time": "2018-06-27 22:44:09",
        "message": "[JTBC 뉴스룸] 아파트 개발 지역에 '축사' 알 박기… 보상 위해 물도 먹이도 없이 방치된 수백 마리 개. 상인들은 적절한 보상이 이뤄지면 축사를 철거하겠다고 했으나 수백 마리의 개를 어떻게 처리할지에… https://t.co/Bwc8Vt7HtA",
        "name": "JTBC_news",
        "num_likes": 65,
        "num_shares": 302,
        "post_id": "1011968428989485057"
    },
    {
        "created_time": "2018-06-27 22:37:04",
        "message": "[JTBC 뉴스룸] 6만원이면 가짜 면허증 몇 시간 만에 '뚝딱'…10대의 비극 된 렌터카. 면허가 없는 미성년자들이 내는 사고가 매년 천여 건에 달해 https://t.co/gWXms4k85r https://t.co/Yms5bHPK1e",
        "name": "JTBC_news",
        "num_likes": 35,
        "num_shares": 106,
        "post_id": "1011966647429558273"
    },
    {
        "created_time": "2018-06-27 22:31:21",
        "message": "[JTBC 뉴스룸] 부산·울산·경남 여당 단체장, '가덕도 신공항' 재추진 뜻 밝혀. '밀양 공항' 추진하던 자유한국당 소속의 대구·경북 단체장들과 대립 구도…여야 '지방 권력' 대결 양상… https://t.co/xhiVbfJUfW",
        "name": "JTBC_news",
        "num_likes": 26,
        "num_shares": 28,
        "post_id": "1011965205381722112"
    },
    {
        "created_time": "2018-06-27 22:24:09",
        "message": "[JTBC 뉴스룸] #날씨 #장마 남부지방 밤새 많은 비 예상…주말에는 중부에도 비. 제주공항에서 항공기 번개 맞는 등 피해 속출 https://t.co/RyV9vdYKSx https://t.co/FjD7ytSodY",
        "name": "JTBC_news",
        "num_likes": 14,
        "num_shares": 35,
        "post_id": "1011963396311298048"
    },
    {
        "created_time": "2018-06-27 22:19:55",
        "message": "[JTBC 뉴스룸] 세종시 건설현장 화재, '기름 증기' 폭발 추정… 장마에 대비해 지하에 쌓아둔 단열재가 불쏘시개 역할. 사고 현장에 대한 정밀 감식은 내일(28일) 이뤄질 예정… https://t.co/taQDSBUdTZ",
        "name": "JTBC_news",
        "num_likes": 16,
        "num_shares": 16,
        "post_id": "1011962330807033859"
    },
    {
        "created_time": "2018-06-27 22:14:44",
        "message": "[JTBC 뉴스룸] \"답답하다\" 규제혁신회의 전격 취소 '군기 잡기'…부처 준비 어땠길래. 문 대통령, 회의 연기 후 \"더욱 속도 내달라\"고 부처들에 당부 https://t.co/M5wHOEhcoM https://t.co/oaSUK7wTFi",
        "name": "JTBC_news",
        "num_likes": 30,
        "num_shares": 28,
        "post_id": "1011961024998567936"
    },
    {
        "created_time": "2018-06-27 21:49:32",
        "message": "[JTBC 뉴스룸] #인터뷰 #월드컵 곧 독일과 '벼랑 끝 승부'… 독일을 가장 잘 아는 '차붐 전설' #차범근 전 국가대표 감독의 분석을 들어봤습니다. https://t.co/zd96bMkWYH https://t.co/hWM0IW1RS1",
        "name": "JTBC_news",
        "num_likes": 24,
        "num_shares": 13,
        "post_id": "1011954684452433926"
    },
    {
        "created_time": "2018-06-27 20:56:21",
        "message": "[JTBC 뉴스룸] '드루킹 특검' 최장 90일 수사 개시. 증거에 따라 수사하겠다는 특검, 자료 분석 과정에서 \"유의미한 자료\" 언급하기도. https://t.co/zeMLbJGI0e https://t.co/OpXLtA4fYM",
        "name": "JTBC_news",
        "num_likes": 16,
        "num_shares": 17,
        "post_id": "1011941301674098688"
    },
    {
        "created_time": "2018-06-27 20:20:18",
        "message": "[JTBC 뉴스룸] 과거·증거 지워버린 법원, #디가우징 파문. 특히 블랙리스트 의혹 재조사 직전에 작업이 진행돼 그 경위를 수사해야 한다는 지적. https://t.co/IBgAj1JU90 https://t.co/ANNB6ifxk5",
        "name": "JTBC_news",
        "num_likes": 35,
        "num_shares": 57,
        "post_id": "1011932227221909504"
    },
    {
        "created_time": "2018-06-27 19:47:06",
        "message": "[JTBC 뉴스룸] JTBC 온에어 ▶https://t.co/M9LrkW7Qww  네이버ㆍ다음ㆍ네이트ㆍ유튜브를 통해 실시간 시청 가능합니다. https://t.co/lpzHqQW8YV",
        "name": "JTBC_news",
        "num_likes": 7,
        "num_shares": 5,
        "post_id": "1011923873078493184"
    },
    {
        "created_time": "2018-06-27 19:46:52",
        "message": "[JTBC 뉴스룸] 6월 27일 주요뉴스 ● 퇴임날 디가우징 지시…한달 뒤 '작업' ● '드루킹 특검' 최대 90일 수사 돌입 ● \"답답하다\" 규제혁신회의 전격 취소 ● 등록금 보태려 아버지 따라 나왔다가… ● 장마전선 '남하'…밤부터 비 쏟아내",
        "name": "JTBC_news",
        "num_likes": 19,
        "num_shares": 12,
        "post_id": "1011923811799785475"
    },
    {
        "created_time": "2018-06-27 16:55:41",
        "message": "배수로에 쌓이는 흙과 돌…가리왕산, 산사태 대비는 아직. 산 아래 주민들은 불안. https://t.co/CiRLg8X4yZ",
        "name": "JTBC_news",
        "num_likes": 17,
        "num_shares": 31,
        "post_id": "1011880734288515072"
    },
    {
        "created_time": "2018-06-27 15:01:28",
        "message": "낚싯배로 무단 이탈...무비자 입국제도를 악용해서 제주로 들어와 뭍으로 나가려던 중국인 검거. 합법 체류기간 끝나자 육지로 밀항 시도. https://t.co/NUS9KSCI0h https://t.co/KOGfVsEegO",
        "name": "JTBC_news",
        "num_likes": 27,
        "num_shares": 83,
        "post_id": "1011851988890312704"
    },
    {
        "created_time": "2018-06-27 14:01:35",
        "message": "길 가다 날벼락...오피스텔 15층서 투신한 여성이 행인 위로 떨어지는 사고 발생. 투신 여성은 숨지고 행인은 팔을 다친 것으로 알려져. https://t.co/M0OkrwSaVe https://t.co/eIjIxYmf8A",
        "name": "JTBC_news",
        "num_likes": 28,
        "num_shares": 73,
        "post_id": "1011836918521184256"
    },
    {
        "created_time": "2018-06-27 12:00:27",
        "message": "포항 앞바다 돌고래 500마리 헤엄 '장관'...포항 연안은 우리나라에서 돌고래를 가장 자주 목격할 수 있는 곳으로 '대륙사면' 지형인 것으로 알려져. https://t.co/U4MLpTflwF https://t.co/93eh2ZCYHH",
        "name": "JTBC_news",
        "num_likes": 51,
        "num_shares": 78,
        "post_id": "1011806434957201409"
    },
    {
        "created_time": "2018-06-27 11:12:13",
        "message": "장맛비에도 초미세먼지 '나쁨' 수준. 먼지 입자들이 비와 함께 지표면으로 떨어진 게 큰 원인. 입자가 작아 비를 빗겨갈 가능성도 있다고 지적. https://t.co/ZLSUaia5KD https://t.co/jP3RTDpMxI",
        "name": "JTBC_news",
        "num_likes": 16,
        "num_shares": 88,
        "post_id": "1011794296050147328"
    },
    {
        "created_time": "2018-06-27 10:12:44",
        "message": "장자연 성추행 전직 기자 기소...9년 만에 뒤집힌 결론. 과거 '신빙성 부족'으로 무혐의 처분되었으나, 목격자 진술 등 추가 정황 확인. https://t.co/BrKJu8CSVQ https://t.co/NXRruX2tPb",
        "name": "JTBC_news",
        "num_likes": 240,
        "num_shares": 912,
        "post_id": "1011779328202268672"
    },
    {
        "created_time": "2018-06-27 09:48:42",
        "message": "#날씨 남부 장맛비 계속...대부분 지역 '호우특보' 대상. 전남·경남·제주에 내일까지 50~100mm 더 내릴 것으로 예상. 낮 기온은 서울 28도, 전주·대구 30도까지 오를 전망.… https://t.co/y0nfbVrJfq",
        "name": "JTBC_news",
        "num_likes": 20,
        "num_shares": 64,
        "post_id": "1011773282276610048"
    },
    {
        "created_time": "2018-06-27 09:47:40",
        "message": "미 캘리포니아 산불 비상…여의도 면적 130배 피해. 클리어 레이크 옥스에서 번지기 시작해 최소 400㎢ 불에 타고 건물 20여 채 피해. https://t.co/svhy1HJqzF https://t.co/MNNnRMOsJo",
        "name": "JTBC_news",
        "num_likes": 18,
        "num_shares": 26,
        "post_id": "1011773018702426112"
    },
    {
        "created_time": "2018-06-27 09:46:54",
        "message": "해리스 주한 미 대사 지명자, 상원 외교위 인준표결 '만장일치' 통과. 공식 임명돼 한국으로 부임하면 대사 공백 사태가 해소 될 것으로 전망. https://t.co/RqpmNNkmC5 https://t.co/y9twA9LxJM",
        "name": "JTBC_news",
        "num_likes": 17,
        "num_shares": 10,
        "post_id": "1011772825714085888"
    },
    {
        "created_time": "2018-06-27 09:46:07",
        "message": "트럼프 손 들어준 미 대법...\"이슬람권 5개국 국민 입국금지, 정당\". 이란·예멘·리비아·소말리아·시리아 해당. 무슬림 단체 반발. https://t.co/QcTMQebyHO https://t.co/zH2FmzHqVe",
        "name": "JTBC_news",
        "num_likes": 19,
        "num_shares": 57,
        "post_id": "1011772632113377280"
    },
    {
        "created_time": "2018-06-27 09:45:07",
        "message": "'삼성 노조와해 자문' 전 노동부장관 보좌관 구속.정치권과 민주노총의 내부 정보를 수집해서 삼성 측에 전달하고 자문료 받아 챙긴 혐의. https://t.co/LxW78FkgQa https://t.co/GdoG2QOAZj",
        "name": "JTBC_news",
        "num_likes": 43,
        "num_shares": 94,
        "post_id": "1011772379641479169"
    },
    {
        "created_time": "2018-06-27 08:42:48",
        "message": "[속보] '탈세·횡령 등 혐의' 조양호 한진그룹 회장 내일 소환조사",
        "name": "JTBC_news",
        "num_likes": 76,
        "num_shares": 138,
        "post_id": "1011756696660684800"
    },
    {
        "created_time": "2018-06-27 06:44:39",
        "message": "6월 27일 JTBC 아침&amp; 예고 ●'경제 라인' 교체…민생 성과 속도 ●'노조 와해 기획' 전 보좌관 구속 ●'장자연 성추행' 전직 기자 기소 ●미 캘리포니아 북부 산불 초비상 https://t.co/b2OlfztAj1",
        "name": "JTBC_news",
        "num_likes": 18,
        "num_shares": 12,
        "post_id": "1011726963638091776"
    },
    {
        "created_time": "2018-06-26 23:49:54",
        "message": "[JTBC 뉴스룸] #다시보기▶https://t.co/M9LrkW7Qww ● 검찰 \"양승태 디가우징 PC라도 달라\"…강제 수사 무게 ● '대 이은' 철도 사랑…북, 실무회담 시작부터 강한 의지 ● '삼성 노… https://t.co/tPmXypcu8w",
        "name": "JTBC_news",
        "num_likes": 20,
        "num_shares": 14,
        "post_id": "1011622589267996677"
    },
    {
        "created_time": "2018-06-26 23:46:33",
        "message": "[JTBC 뉴스룸] #앵커브리핑 '여러분은 이걸 장난감이라 할지 모르겠지만…' https://t.co/VUTKBy1ka9 비록 작고 가벼워도 지니고 있는 무게와 상징성만큼은 결코 가볍지 않은 훈장. 망자는… https://t.co/TuD9ziTcLV",
        "name": "JTBC_news",
        "num_likes": 34,
        "num_shares": 24,
        "post_id": "1011621743562125314"
    },
    {
        "created_time": "2018-06-26 23:34:58",
        "message": "[JTBC 뉴스룸] #팩트체크 툭하면 지연되는 항공기에 피해를 입는 이용객들이 많은데 그렇다면 배상을 받을 수는 없는 것인지 팩트체크 팀에서 알아봤습니다. https://t.co/FYHMDzMAeb https://t.co/ZMAtiLTw6f",
        "name": "JTBC_news",
        "num_likes": 30,
        "num_shares": 41,
        "post_id": "1011618828235624449"
    },
    {
        "created_time": "2018-06-26 23:29:34",
        "message": "[JTBC 뉴스룸] #인터뷰 '이인규 입장문 논란'에 대해 노무현 전 대통령 변호인이었던 #전해철 더불어민주당 의원의 입장을 들어봤습니다. https://t.co/gSdCnoCTj0 https://t.co/kiCCx3Vdri",
        "name": "JTBC_news",
        "num_likes": 28,
        "num_shares": 20,
        "post_id": "1011617470333870080"
    },
    {
        "created_time": "2018-06-26 23:24:39",
        "message": "[JTBC 뉴스룸] 포항 앞바다에서 돌고래 500마리가 헤엄치는 모습 포착. 돌고래가 좋아하는 두족류나 어류가 많이 분포해 자주 목격. 주로 봄에서 가을 사이 먹이를 따라 무리 지어 이동… https://t.co/RervdN6byG",
        "name": "JTBC_news",
        "num_likes": 57,
        "num_shares": 56,
        "post_id": "1011616231747534850"
    },
    {
        "created_time": "2018-06-26 23:19:49",
        "message": "[JTBC 뉴스룸] #밀착카메라 기약 없이 늦어지는 도로 공사…교통난에 안전까지 위협. 시행사와 지자체의 대책 마련이 시급해 https://t.co/xTUoqphQtt https://t.co/D5DGxx7fa2",
        "name": "JTBC_news",
        "num_likes": 13,
        "num_shares": 10,
        "post_id": "1011615015869149187"
    },
    {
        "created_time": "2018-06-26 23:13:54",
        "message": "[JTBC 뉴스룸] 심상치 않은 '1㎝'…지진 이후 솟아오른 포항 흥해읍 일대. 강진 발생 가능성 있어 지진방재나 안전 대책을 미리 세워야 한다는 경고도 https://t.co/3mHlJ1NvHO https://t.co/dnCqZWMoOR",
        "name": "JTBC_news",
        "num_likes": 36,
        "num_shares": 148,
        "post_id": "1011613526304030721"
    },
    {
        "created_time": "2018-06-26 23:06:41",
        "message": "[JTBC 뉴스룸] 검찰 재수사로 '장자연 사건 연루' 전 조선일보 기자 기소. 9년 전엔 '목격자 신빙성 부족하다'며 불기소 처분했으나 재수사 결과, 목격자 진술을 믿을만한 추가 정황 확인해… https://t.co/bOsvENX8ZN",
        "name": "JTBC_news",
        "num_likes": 56,
        "num_shares": 119,
        "post_id": "1011611713525858305"
    },
    {
        "created_time": "2018-06-26 23:02:26",
        "message": "[JTBC 뉴스룸] 배차 간격 99분 \"운 좋아야 탄다\"… '주 52시간 근무제' 앞두고 지방 '버스 대란' 예고. 단축 근로로 인해 수입이 줄어들 것을 걱정한 기사들이 급여 높은 서울에 몰려… https://t.co/BV2T0BFXk1",
        "name": "JTBC_news",
        "num_likes": 27,
        "num_shares": 52,
        "post_id": "1011610640673226757"
    },
    {
        "created_time": "2018-06-26 22:58:25",
        "message": "[JTBC 뉴스룸] 김포공항서 대한항공-아시아나 여객기 접촉 사고. 보조엔진 실린 꼬리날개, 시동 걸렸다면 '아찔'…비슷한 사고가 잇따라 일어나면서 항공사와 공항 운영사에 대한 철저한 안전 감독이 필요하다는… https://t.co/4Z51ddJJ3k",
        "name": "JTBC_news",
        "num_likes": 16,
        "num_shares": 40,
        "post_id": "1011609629338431490"
    },
    {
        "created_time": "2018-06-26 22:51:21",
        "message": "[JTBC 뉴스룸] 무면허 10대, 빗길에 렌터카 몰다 건물 들이받아 탑승한 중고생 4명 숨져. 경찰은 면허가 없는 학생들이 어떻게 차량을 빌렸는지와 운전자의 음주 여부 등도 확인 중… https://t.co/DUzkgLIeHG",
        "name": "JTBC_news",
        "num_likes": 25,
        "num_shares": 85,
        "post_id": "1011607854086873091"
    },
    {
        "created_time": "2018-06-26 22:47:05",
        "message": "[JTBC 뉴스룸] 장맛비 내렸는데도 초미세먼지 '나쁨'…대기 상층부에 있던 먼지 입자들이 빗방울과 함께 내려 땅 위에 쌓인 먼지를 튀게 했다는 분석도 https://t.co/xVKJe3cryW https://t.co/5bsr2wbNQ9",
        "name": "JTBC_news",
        "num_likes": 32,
        "num_shares": 111,
        "post_id": "1011606779216551936"
    },
    {
        "created_time": "2018-06-26 22:40:34",
        "message": "[JTBC 뉴스룸] 폭발 소리 나고 불길 치솟아…세종시 건설현장에서 화재로 3명 사망. 단열재 쌓여 있고, 소방설비 갖춰져 있지 않아 피해 커져. 소방당국, 발화 흔적 흩어져 있어 정확한 발화지점 찾기 어려… https://t.co/knXhpFdCfN",
        "name": "JTBC_news",
        "num_likes": 16,
        "num_shares": 47,
        "post_id": "1011605138023288832"
    },
    {
        "created_time": "2018-06-26 20:39:44",
        "message": "[JTBC 뉴스룸] 양승태 PC '디가우징' 파문…대법, 검찰에 410개 파일만 제출. 넘긴 파일 상당수는 이미 알려진 내용으로 속빈 강정이라는 지적도. https://t.co/HxmAXpphK7 https://t.co/WPf404d17x",
        "name": "JTBC_news",
        "num_likes": 58,
        "num_shares": 103,
        "post_id": "1011574731600883712"
    },
    {
        "created_time": "2018-06-26 20:29:55",
        "message": "[JTBC 뉴스룸] 청와대 '경제라인' 인사 개편 단행…경제수석에 윤종원, 일자리수석에 정태호. 사실상 문책성 교체라는 분석이 지배적. https://t.co/YKf61qLz6i https://t.co/X30rFLroIs",
        "name": "JTBC_news",
        "num_likes": 17,
        "num_shares": 14,
        "post_id": "1011572258639249408"
    },
    {
        "created_time": "2018-06-26 19:48:33",
        "message": "[JTBC 뉴스룸] JTBC 온에어 ▶https://t.co/M9LrkW7Qww  네이버ㆍ다음ㆍ네이트ㆍ유튜브를 통해 실시간 시청 가능합니다. https://t.co/lpzHqQW8YV",
        "name": "JTBC_news",
        "num_likes": 13,
        "num_shares": 3,
        "post_id": "1011561850306084865"
    },
    {
        "created_time": "2018-06-26 19:47:52",
        "message": "[JTBC 뉴스룸] 6월 26일 주요뉴스 ● 청와대 경제라인 '문책성' 교체 ● 양승태 컴퓨터 '디가우징' 파문 ● 세종시 건설현장 화재…3명 숨져 ● 장마 시작…내일 남부 최고 200㎜",
        "name": "JTBC_news",
        "num_likes": 17,
        "num_shares": 9,
        "post_id": "1011561677987254273"
    },
    {
        "created_time": "2018-06-26 16:18:12",
        "message": "오늘(26일) 밤 JTBC 뉴스룸에선 노무현 전 대통령의 변호인이었던 전해철 더불어민주당 의원으로부터, 이른바 '논두렁 시계' 사건과 관련한 검찰과 국정원의 공작 의혹에 대해 들어봅니다. 많은 시청 바랍니다. https://t.co/nXFQ4nQD0s",
        "name": "JTBC_news",
        "num_likes": 147,
        "num_shares": 227,
        "post_id": "1011508911524868096"
    },
    {
        "created_time": "2018-06-26 15:39:18",
        "message": "[속보] 대법 '재판거래' 의혹파일 원본 검찰 제출...하드디스크 제외",
        "name": "JTBC_news",
        "num_likes": 37,
        "num_shares": 108,
        "post_id": "1011499124712075264"
    },
    {
        "created_time": "2018-06-26 14:06:37",
        "message": "주유소·공원·마트 돌아다니며 '묻지마 폭행'한 40대 남성. 경찰 조사 결과 \"과거 조현병 확인\". 최씨에 대해 특수상해 혐의로 구속영장 신청. https://t.co/SoCj6QEkko https://t.co/dEQsyXN6RL",
        "name": "JTBC_news",
        "num_likes": 17,
        "num_shares": 43,
        "post_id": "1011475798383923200"
    },
    {
        "created_time": "2018-06-26 13:06:48",
        "message": "\"국정원이 배후\" vs \"취재원은 대검\"…논두렁 시계 보도 경위 둘러싼 진실공방 가열. https://t.co/IgwQDHmK0c https://t.co/5m10epsJVI",
        "name": "JTBC_news",
        "num_likes": 22,
        "num_shares": 40,
        "post_id": "1011460745538629632"
    },
    {
        "created_time": "2018-06-26 12:47:24",
        "message": "\"라돈침대 반입 반대\"...당진 주민에 이어 대진침대 본사 주변 천안 주민도 반발. 본사 입구에서부터 차단해 화물차 10대가 그대로 돌아가는 등 처리 작업에 난항. https://t.co/xxMwE0qTEr https://t.co/R1bbQNH4TX",
        "name": "JTBC_news",
        "num_likes": 19,
        "num_shares": 36,
        "post_id": "1011455862584430592"
    },
    {
        "created_time": "2018-06-26 10:33:20",
        "message": "\"오늘이 마지막일 수도 있으니까\" 이산가족 상봉 후보자 500명 선정 현장. 참석 여부와 추첨 가능성은 상관이 없지만, 간절한 마음에 이 자리에 나온 분들이 있어 눈길.… https://t.co/PORepjtbrN",
        "name": "JTBC_news",
        "num_likes": 58,
        "num_shares": 157,
        "post_id": "1011422123343015936"
    },
    {
        "created_time": "2018-06-26 09:40:09",
        "message": "한예종 '성폭력 의혹' 교수 징계. 만화가 박재동 교수·영화 '왕의 남자' 원작자 김태웅 교수는 정직 3개월, 시인 황지우 교수는 정직 1개월이 결정. https://t.co/jEuxBcc7nl https://t.co/ugCBl0go9p",
        "name": "JTBC_news",
        "num_likes": 46,
        "num_shares": 372,
        "post_id": "1011408741986717696"
    },
    {
        "created_time": "2018-06-26 09:39:29",
        "message": "MB정부 '노총 파괴공작' 이채필 전 고용노동부 장관 소환…양대 노총 분열공작 의혹에 개입한 혐의. 구속영장 청구 여부 검토 예정. https://t.co/VVVSS9L65U https://t.co/WfnuI6tRxs",
        "name": "JTBC_news",
        "num_likes": 26,
        "num_shares": 36,
        "post_id": "1011408573744627712"
    },
    {
        "created_time": "2018-06-26 09:38:56",
        "message": "북한, 올해는 6·25 반미 집회 안 열어...북한 매체의 관련 보도 또한 없었던 것으로 알려져. 미 AP 통신은 \"긴장 완화의 신호\"라고 평가. https://t.co/FZTFP8vKkZ https://t.co/DXULPtWdPN",
        "name": "JTBC_news",
        "num_likes": 29,
        "num_shares": 22,
        "post_id": "1011408432656670721"
    },
    {
        "created_time": "2018-06-26 09:38:15",
        "message": "본격 장마 시작...중부 최대 120mm. 충청·남부 내일부터 돌풍·번개 동반한 많은 비. 오는 30일 잠시 소강 상태보였다가 다음달 1일 쯤 다시 비를 뿌릴 것으로 전망.… https://t.co/4myeWhaRmg",
        "name": "JTBC_news",
        "num_likes": 58,
        "num_shares": 426,
        "post_id": "1011408262548164608"
    },
    {
        "created_time": "2018-06-26 09:23:21",
        "message": "[속보] 김포공항서 대한항공-아시아나기 접촉사고...기체 일부 손상",
        "name": "JTBC_news",
        "num_likes": 77,
        "num_shares": 858,
        "post_id": "1011404511271768064"
    },
    {
        "created_time": "2018-06-26 06:46:39",
        "message": "6월 26일 JTBC 아침&amp; 예고 ●강진 야산 시신 실종 여고생 확인 ●\"논두렁 시계 보도 배후는 원세훈\" ●'노총 와해 공작 의혹' 이채필 소환 ●본격 장마 시작…내일까지 많은 비 https://t.co/b2OlfztAj1",
        "name": "JTBC_news",
        "num_likes": 9,
        "num_shares": 13,
        "post_id": "1011365078921199617"
    },
    {
        "created_time": "2018-06-25 23:56:17",
        "message": "[JTBC 뉴스룸] #다시보기▶https://t.co/M9LrkW7Qww ● \"배후는 국정원\" vs \"취재원은 대검\" 보도 경위 진실게임 ● \"라돈침대 반입 반대\"…이번엔 천안 본사 지역 주민 반발 ● 트럼… https://t.co/NukFDNGYM7",
        "name": "JTBC_news",
        "num_likes": 13,
        "num_shares": 5,
        "post_id": "1011261807443365888"
    },
    {
        "created_time": "2018-06-25 23:53:36",
        "message": "[JTBC 뉴스룸] #팩트체크 김종필 전 총리에 국민훈장 중 최고등급 '무궁화장'…관례 따른 것? 무궁화 대훈장과 무궁화장의 차이는? https://t.co/kwnX0rhZSy https://t.co/SdF5u1Wwly",
        "name": "JTBC_news",
        "num_likes": 30,
        "num_shares": 29,
        "post_id": "1011261129597771777"
    },
    {
        "created_time": "2018-06-25 23:24:53",
        "message": "[JTBC 뉴스룸] #앵커브리핑 \"오늘은 땡이 아니라 딩동댕을 쳐드리고 싶습니다\" https://t.co/7PYe8AAqRA 세상은 우리가 지나온 3김의 시대를 부정하려는 것이 아니라, 소수의 정치지도자에게… https://t.co/ggMfBEXxPy",
        "name": "JTBC_news",
        "num_likes": 65,
        "num_shares": 54,
        "post_id": "1011253905127165963"
    },
    {
        "created_time": "2018-06-25 23:18:24",
        "message": "[JTBC 뉴스룸] 환경호르몬 검출된 대구 수돗물, 환경부 차관이 직접 마시며 \"안전하다\" 강조했지만…시민들 불안감은 여전. https://t.co/NmPL7zf82K https://t.co/2zb2UCAPTr",
        "name": "JTBC_news",
        "num_likes": 19,
        "num_shares": 81,
        "post_id": "1011252273651937280"
    },
    {
        "created_time": "2018-06-25 22:45:04",
        "message": "[JTBC 뉴스룸] 총수지분 29.9% 맞추기 '꼼수'…일감 몰아주기 규제에도 내부거래 급증. 공정위가 제도 개선 방안을 마련할 예정. https://t.co/311tWzqCug https://t.co/4cS6ITgilj",
        "name": "JTBC_news",
        "num_likes": 25,
        "num_shares": 29,
        "post_id": "1011243881491398657"
    },
    {
        "created_time": "2018-06-25 22:30:59",
        "message": "[JTBC 뉴스룸] 한국당 '쇄신 주도권' 놓고 계파 갈등 극심. 오늘(25일)도 친박계는 다양한 경로를 통해 김성태 대표 권한대행의 사퇴 촉구. https://t.co/KDASmLZCTp https://t.co/bWPRf8KUjj",
        "name": "JTBC_news",
        "num_likes": 17,
        "num_shares": 16,
        "post_id": "1011240337539387392"
    },
    {
        "created_time": "2018-06-25 22:12:22",
        "message": "[JTBC 뉴스룸] 미, 곧 북에 '비핵화 시간표' 제시할 듯. 여기에 특정 요구사항이 담길 것으로 관측돼 구체적인 압박 메시지로 풀이. https://t.co/q5fXNS1NY0 https://t.co/BJ85eAzjkI",
        "name": "JTBC_news",
        "num_likes": 24,
        "num_shares": 17,
        "post_id": "1011235655077117953"
    },
    {
        "created_time": "2018-06-25 20:50:34",
        "message": "[JTBC 뉴스룸] '장자연 사건' 본조사 결정 연기…재논의 시간 부족해 한 주 미뤄. 재조사 시 조선일보 관계자 축소 수사 의혹 집중 확인할 듯. https://t.co/QLWl9yHdd4 https://t.co/OyW9KOiYuk",
        "name": "JTBC_news",
        "num_likes": 150,
        "num_shares": 501,
        "post_id": "1011215066627108867"
    },
    {
        "created_time": "2018-06-25 20:32:00",
        "message": "[JTBC 뉴스룸] \"원세훈이 꾸민 일…검찰은 거절했다\" 논두렁 시계 보도 책임 다시 부인하고 나선 이인규 전 대검 중수부장. https://t.co/57l1q8fZIY https://t.co/fdiNjxIOA2",
        "name": "JTBC_news",
        "num_likes": 34,
        "num_shares": 60,
        "post_id": "1011210395766304768"
    },
    {
        "created_time": "2018-06-25 20:01:39",
        "message": "[JTBC 뉴스룸] JTBC 온에어 ▶https://t.co/M9LrkW7Qww 네이버ㆍ다음ㆍ네이트ㆍ유튜브를 통해 실시간 시청 가능합니다. https://t.co/lpzHqQW8YV",
        "name": "JTBC_news",
        "num_likes": 9,
        "num_shares": 3,
        "post_id": "1011202758467203072"
    },
    {
        "created_time": "2018-06-25 20:01:09",
        "message": "[JTBC 뉴스룸] 6월 25일 주요뉴스 ● 이인규 \"논두렁 시계 보도…배후는 원세훈\" ● 장자연 사건' 재조사 권고 여부 다음주로 ● \"미, 비핵화 '시간표' 곧 북에 제시\" ● 한국당 갈등 격화…\"김성태… https://t.co/IIm2riXAko",
        "name": "JTBC_news",
        "num_likes": 23,
        "num_shares": 23,
        "post_id": "1011202631082041345"
    },
    {
        "created_time": "2018-06-25 15:13:24",
        "message": "#취재설명서 \"조선일보 최보식 칼럼, 정정보도 요청합니다!\" https://t.co/hwbFQE2t1E 터무니없는 '최순실 태블릿PC 조작설'. 칼럼은 개인 주장과 의견을 담을 수 있지만... 칼럼이라는 이… https://t.co/0VTX0QhU15",
        "name": "JTBC_news",
        "num_likes": 36,
        "num_shares": 28,
        "post_id": "1011130218226913280"
    },
    {
        "created_time": "2018-06-25 14:11:09",
        "message": "더위도 힘든데 초미세먼지·자외선·오존까지 '극성'. 오존에 장시간 노출 될 경우 폐와 심장에 영향을 줄 수도 있어 유의. https://t.co/AkAHDwS1Kp https://t.co/x11DJ8ZXux",
        "name": "JTBC_news",
        "num_likes": 35,
        "num_shares": 131,
        "post_id": "1011114551763275776"
    },
    {
        "created_time": "2018-06-25 13:11:15",
        "message": "법원, '재판 거래' 자료 요청에 일주일째 침묵...고발인들은 증거 인멸을 우려하며 강제 수사 촉구. 오늘 법원노조 본부장 불러 3차 고발인 조사. https://t.co/QwV65vcT21 https://t.co/41ujogdvsD",
        "name": "JTBC_news",
        "num_likes": 28,
        "num_shares": 53,
        "post_id": "1011099478059700225"
    },
    {
        "created_time": "2018-06-25 12:00:02",
        "message": "미 아동격리정책 후폭풍...트럼프 행정부 관리들 식당에서 쫓겨나는 잇따라 봉변. 정책철회에도 부모재회 아동 500여 명에 불과한 것으로 알려져. https://t.co/dlYza4hmG0 https://t.co/Pck1elNM96",
        "name": "JTBC_news",
        "num_likes": 35,
        "num_shares": 114,
        "post_id": "1011081555450609664"
    },
    {
        "created_time": "2018-06-25 11:22:13",
        "message": "[속보] 청와대 \"JP에 국민훈장 무궁화장 추서\"...문대통령 빈소조문은 안 해",
        "name": "JTBC_news",
        "num_likes": 42,
        "num_shares": 93,
        "post_id": "1011072039589797888"
    },
    {
        "created_time": "2018-06-25 11:20:34",
        "message": "[속보] 남북, 철도 26일·도로 28일·산림 7월4일 분과회의 개최",
        "name": "JTBC_news",
        "num_likes": 104,
        "num_shares": 376,
        "post_id": "1011071625331073024"
    },
    {
        "created_time": "2018-06-25 11:00:44",
        "message": "사륜 오토바이 잇단 사고에도 안전불감증 여전. 법적으로 이륜자동차지만 무면허 운전이 대부분. 기본적 안전장비도 갖추지 않아 사고 잇따라. https://t.co/41lReDuJ5m https://t.co/SF2VOjVrYZ",
        "name": "JTBC_news",
        "num_likes": 18,
        "num_shares": 25,
        "post_id": "1011066630980263937"
    },
    {
        "created_time": "2018-06-25 10:00:15",
        "message": "'판문점→오산기지→미국...'미군 유해' 이번주 송환 예정. 이 과정서 폼페이오 미 국무장관이 함께할 가능성. 북·미회담 합의 항목 중 첫 이행 사례. https://t.co/UVU3K9GPrD https://t.co/cp8fIz9nv2",
        "name": "JTBC_news",
        "num_likes": 18,
        "num_shares": 26,
        "post_id": "1011051409448423424"
    },
    {
        "created_time": "2018-06-25 09:53:27",
        "message": "#날씨 오늘까지 전국 폭염...오늘 밤부터 장마전선 북상하며 더위 주춤. 내일 아침 출근길 전국에 비 예상. 낮 기온은 서울 33도, 광주 33도, 대구 35도까지 오를 전망.… https://t.co/zdLhIwyOOx",
        "name": "JTBC_news",
        "num_likes": 28,
        "num_shares": 220,
        "post_id": "1011049701670391808"
    },
    {
        "created_time": "2018-06-25 09:44:32",
        "message": "트럼프 \"불법 입국자 재판 없이 즉시 추방해야\"...'침략자'로 규정하기도. 미 언론 \"적법한 절차적 권리를 박탈하는 것\"이라고 지적. https://t.co/kKDVmn5yN4 https://t.co/NU89Mte99I",
        "name": "JTBC_news",
        "num_likes": 15,
        "num_shares": 28,
        "post_id": "1011047456627290113"
    },
    {
        "created_time": "2018-06-25 09:17:39",
        "message": "한국당, 6·13 후 첫 원내대책회의 열어 당 수습 방안 등 논의...바른미래당, 의원총회 열어 신임 원내대표 선출. https://t.co/m72cbbCVsR https://t.co/4pWLkediTb",
        "name": "JTBC_news",
        "num_likes": 11,
        "num_shares": 7,
        "post_id": "1011040689549787136"
    },
    {
        "created_time": "2018-06-25 09:17:23",
        "message": "이번 주 판문점·금강산서 실무 접촉 잇따라...오늘(25일) '군 통신선 복구 논의' 실무 접촉. 판문점서 철도·도로 연결 사업 논의할 듯. https://t.co/Ldw4DTbqGM https://t.co/EDtCtarAhf",
        "name": "JTBC_news",
        "num_likes": 36,
        "num_shares": 44,
        "post_id": "1011040623221043200"
    },
    {
        "created_time": "2018-06-25 09:17:02",
        "message": "강진 실종 여고생 수사 속도...이르면 오늘 유전자 감정 결과 발표. 경찰은 강력범죄 연관성 조사, 추가 CCTV 분석해 납치 여부나 범행 동기 등 수사 예정. https://t.co/H5w15rLKpx https://t.co/JgKv2lILO8",
        "name": "JTBC_news",
        "num_likes": 22,
        "num_shares": 70,
        "post_id": "1011040534914260992"
    },
    {
        "created_time": "2018-06-25 06:48:03",
        "message": "6월 25일 JTBC 아침&amp; 예고 ●강진 실종 여고생 추정 시신 발견 ●남북 '군 통신선 복원' 실무 접촉 ●고발인 조사…자료 제출에 '침묵' ●'침략' 표현…\"재판 없이 추방해야\" https://t.co/b2OlfztAj1",
        "name": "JTBC_news",
        "num_likes": 11,
        "num_shares": 17,
        "post_id": "1011003041116385280"
    },
    {
        "created_time": "2018-06-24 22:30:06",
        "message": "[JTBC 뉴스룸] #다시보기 ▶https://t.co/6laMsJLfR1 ● 아이들 탄 회전 그네가 '쿵'…월미도서 또 놀이기구 사고 ● 면허·장비도 없이 '부릉'…사륜 오토바이 '아찔한 질주'● 식당서 쫓겨난 백악관 대변인…미 아동격리정책 후폭풍",
        "name": "JTBC_news",
        "num_likes": 16,
        "num_shares": 18,
        "post_id": "1010877728730411008"
    },
    {
        "created_time": "2018-06-24 22:15:57",
        "message": "[JTBC 뉴스룸] #날씨 25일도 더운 날씨 이어져…제주와 강원 산지 제외하고 대부분 폭염 특보 https://t.co/5vil8E79Eb https://t.co/3xCvXH3V71",
        "name": "JTBC_news",
        "num_likes": 21,
        "num_shares": 42,
        "post_id": "1010874168055697408"
    },
    {
        "created_time": "2018-06-24 22:08:44",
        "message": "[JTBC 뉴스룸] #뉴스브리핑 ● 월세 밀려 보증금 적게 돌려받자 불 질러 ● 소방차에 길 양보 안 하면 100만 원 과태료 ● 삼성증권 투자자들 '배당 오류' 손해배상 소송 ● 공정위, 60개 대기업집단… https://t.co/33yJlcUh6L",
        "name": "JTBC_news",
        "num_likes": 14,
        "num_shares": 12,
        "post_id": "1010872352748404736"
    },
    {
        "created_time": "2018-06-24 22:01:14",
        "message": "[JTBC 뉴스룸] #이슈플러스 치킨 '월드컵 특수', 스웨덴전이 열린 18일에는 치킨 결제 카드 금액이 일주인 전의 133% 기록. 그러나 양계농가는 닭고기 값이 폭락하여 '울상'. 산지-소비자 가격의 괴… https://t.co/q7lw6WerWj",
        "name": "JTBC_news",
        "num_likes": 45,
        "num_shares": 94,
        "post_id": "1010870465718464512"
    },
    {
        "created_time": "2018-06-24 21:50:38",
        "message": "[JTBC 뉴스룸] 고발인들, '재판 거래' 강제수사 촉구…\"의혹 문건들이 이미 지난해 초에 삭제된 흔적이 뚜렷하다.\" 지난 19일 요구한 '전·현직 고위 법관들의 하드 디스크·법인 카드 사용 명세내역 등'… https://t.co/j6O1QpbOYa",
        "name": "JTBC_news",
        "num_likes": 35,
        "num_shares": 38,
        "post_id": "1010867797658775552"
    },
    {
        "created_time": "2018-06-24 21:42:45",
        "message": "[JTBC 뉴스룸] JP 빈소 이틀째 조문 행렬…반기문 전 유엔 사무총장·이회창 전 총리 등 각계 인사들 빈소 찾아. 일부 정치권과 시민단체 등의 반대에도 불구하고, 정부는 김 전 총리에게 국민 훈장의 최고… https://t.co/pGXTgHbUvf",
        "name": "JTBC_news",
        "num_likes": 20,
        "num_shares": 37,
        "post_id": "1010865811307675651"
    },
    {
        "created_time": "2018-06-24 21:29:26",
        "message": "[JTBC 뉴스룸] 서울 첫 폭염주의보…1972년 기상관측을 시작한 이후 6월 최고 기온 기록. 때 이른 이번 더위는 서해상에 머무는 '북태평양고기압' 영향 때문…여기에 태양 고도도 높아져 강한 햇빛이 더해… https://t.co/SU9rJ8CgQp",
        "name": "JTBC_news",
        "num_likes": 30,
        "num_shares": 117,
        "post_id": "1010862461300297728"
    },
    {
        "created_time": "2018-06-24 21:20:17",
        "message": "[JTBC 뉴스룸] 남북 정상 모두 초청한 푸틴…9월, 남·북·러 한자리에 모이나? 김정은 위원장은 비핵화 선언 이후 '경제 발전에 집중하겠다'는 입장인 만큼, 초청에 응할 가능성이 클 것으로 예측. 3국이… https://t.co/Drj4IRozGo",
        "name": "JTBC_news",
        "num_likes": 43,
        "num_shares": 38,
        "post_id": "1010860158799343616"
    },
    {
        "created_time": "2018-06-24 21:10:20",
        "message": "[JTBC 뉴스룸] 실종된 지 8일 만에…강진 야산서 여고생 추정 시신 발견. 이 양의 휴대전화 신호가 마지막으로 잡힌 곳과 가까워. 옷은 벗겨져 있었고 부패도 어느 정도 진행된 상태. 경찰은 DNA 검사·… https://t.co/545Q0UEVNH",
        "name": "JTBC_news",
        "num_likes": 36,
        "num_shares": 177,
        "post_id": "1010857654174900224"
    },
    {
        "created_time": "2018-06-24 19:53:02",
        "message": "[JTBC 뉴스룸] JTBC 온에어 ▶https://t.co/M9LrkW7Qww    네이버ㆍ다음ㆍ네이트ㆍ유튜브를 통해 실시간 시청 가능합니다. https://t.co/o4Za4niEbv",
        "name": "JTBC_news",
        "num_likes": 8,
        "num_shares": 4,
        "post_id": "1010838200447741952"
    },
    {
        "created_time": "2018-06-24 19:50:41",
        "message": "[JTBC 뉴스룸] 6월 24일 주요뉴스 ● '실종 여고생' 추정 시신 발견 ● 영덕 37도 '최고'…폭염특보 확대 ● 한국 2패…16강행 '실낱 희망' ● 9월 남·북·러 정상 함께 만나나 ● 인천 월미도서 놀이기구 사고",
        "name": "JTBC_news",
        "num_likes": 29,
        "num_shares": 14,
        "post_id": "1010837609415708672"
    },
    {
        "created_time": "2018-06-24 02:07:57",
        "message": "[속보] 한국, 멕시코에 1-2로 패배…조별리그 탈락 위기",
        "name": "JTBC_news",
        "num_likes": 39,
        "num_shares": 99,
        "post_id": "1010570164641779716"
    },
    {
        "created_time": "2018-06-23 22:17:45",
        "message": "[JTBC 뉴스룸] #다시보기 ▶https://t.co/6laMsJLfR1  ● '35세 중정부장·45세 총리' 화려한 경력 뒤엔…JP 정치 역정 ● 대법, 검찰 자료요청에 닷새째 '침묵'…\"강제수사\" 목소… https://t.co/S2VshrL8IZ",
        "name": "JTBC_news",
        "num_likes": 16,
        "num_shares": 9,
        "post_id": "1010512235368669184"
    },
    {
        "created_time": "2018-06-23 22:17:09",
        "message": "[JTBC 뉴스룸] 푹푹 찌는 '대프리카' 더위 '과학'으로 잡는다… 인공 안개비·차열페인트 등 다양한 방법 동원 https://t.co/bGcYAVBBWr https://t.co/q0MmsFUghn",
        "name": "JTBC_news",
        "num_likes": 22,
        "num_shares": 43,
        "post_id": "1010512084029730821"
    },
    {
        "created_time": "2018-06-23 22:12:22",
        "message": "[JTBC 뉴스룸] 미국 울린 '두 살배기 소녀의 울음'… 불법 이민자 자녀를 격리하는 것에 대해 비판이 일면서 이민자 성금 '밀물' https://t.co/02Or14QQzu https://t.co/gK5vgn7NFu",
        "name": "JTBC_news",
        "num_likes": 28,
        "num_shares": 48,
        "post_id": "1010510880054771713"
    },
    {
        "created_time": "2018-06-23 22:08:08",
        "message": "[JTBC 뉴스룸] #이슈플러스 몰카범 신고했다가 되레 경찰에 2차 피해를 봤다는 주장 나와. '뭐가 수치스럽냐'는 식으로 반문해… 성범죄에 대한 일선 경찰의 안일한 인식에 갈 곳 잃은 피해자… https://t.co/csGdg92ndI",
        "name": "JTBC_news",
        "num_likes": 55,
        "num_shares": 211,
        "post_id": "1010509811736178688"
    },
    {
        "created_time": "2018-06-23 22:01:16",
        "message": "[JTBC 뉴스룸] 미군 전사자 '유해송환 절차' 시작. 미군, 판문점을 통해 북측에 임시운송케이스 100여 개 전달. 지난 싱가포르 북미회담 합의 내용 첫 이행 https://t.co/VgWX0TuPpo https://t.co/r8WkqTIps0",
        "name": "JTBC_news",
        "num_likes": 23,
        "num_shares": 22,
        "post_id": "1010508084395978752"
    },
    {
        "created_time": "2018-06-23 21:49:34",
        "message": "[JTBC 뉴스룸] 여야 지도부, 김종필 전 총리 별세에 대해 애도 한 목소리… 정치적 평가는 엇갈려. 청와대 \"현대 정치사 족적 지워지지 않을 것\" https://t.co/LnHLi9cg2j https://t.co/3t16XFmiQU",
        "name": "JTBC_news",
        "num_likes": 13,
        "num_shares": 15,
        "post_id": "1010505139298299904"
    },
    {
        "created_time": "2018-06-23 21:44:34",
        "message": "[JTBC 뉴스룸] 김종필 전 총리, 향년 92세로 별세. '3김' 모두 역사 속으로…27일까지 닷새 동안 '가족장'으로 장례 https://t.co/JkM44FSAB1 https://t.co/4KVCSE0NKw",
        "name": "JTBC_news",
        "num_likes": 23,
        "num_shares": 19,
        "post_id": "1010503883129479168"
    },
    {
        "created_time": "2018-06-23 19:52:10",
        "message": "[JTBC 뉴스룸] JTBC 온에어 ▶https://t.co/M9LrkW7Qww  네이버ㆍ다음ㆍ네이트ㆍ유튜브를 통해 실시간 시청 가능합니다. https://t.co/o4Za4niEbv",
        "name": "JTBC_news",
        "num_likes": 7,
        "num_shares": 3,
        "post_id": "1010475595749195777"
    },
    {
        "created_time": "2018-06-23 19:51:34",
        "message": "[JTBC 뉴스룸] 6월 23일 주요뉴스 ● 김종필 전 총리 별세…'3김' 역사 속으로 ● 미군 전사자 '유해송환 절차' 시작 ● 트럼프, 대북제재 연장…비핵화 압박 ● \"몰카 신고했다가 2차 피해\" 주장",
        "name": "JTBC_news",
        "num_likes": 14,
        "num_shares": 6,
        "post_id": "1010475445526020096"
    },
    {
        "created_time": "2018-06-23 17:12:31",
        "message": "한·러 정상, 한반도 완전한 비핵화, 항구적 평화체제 구축에 협력키로. 푸틴 대통령은 러시아도 북핵문제 해결에 적극 나서겠다는 의지 밝혀. https://t.co/6sSCl2x7pb https://t.co/cpkOWvQ4ma",
        "name": "JTBC_news",
        "num_likes": 51,
        "num_shares": 29,
        "post_id": "1010435420180496385"
    },
    {
        "created_time": "2018-06-23 17:12:11",
        "message": "트럼프 미 대통령, 대북제재 1년 연장 통지…북미 회담 이후에도 비핵화 없이 제재 해제하지 않겠다는 원칙 강조한 것으로 관측. https://t.co/XMMkzgJ1H7 https://t.co/9VeOAvxv9Q",
        "name": "JTBC_news",
        "num_likes": 24,
        "num_shares": 32,
        "post_id": "1010435336495927296"
    },
    {
        "created_time": "2018-06-23 17:11:44",
        "message": "김종필 전 국무총리, 향년 92세 일기로 별세. 3김 시대 주역으로 한국 정치사에 족적 남겨…아산병원에 빈소 마련, 정치권 조문 줄 이을 듯. https://t.co/mBjTeZWTg0 https://t.co/wtW5b1UYeK",
        "name": "JTBC_news",
        "num_likes": 20,
        "num_shares": 22,
        "post_id": "1010435223400603648"
    },
    {
        "created_time": "2018-06-23 09:55:37",
        "message": "[속보] 김종필 전 국무총리 별세",
        "name": "JTBC_news",
        "num_likes": 72,
        "num_shares": 491,
        "post_id": "1010325467491008512"
    },
    {
        "created_time": "2018-06-22 21:52:53",
        "message": "[JTBC 뉴스룸] #다시보기▶https://t.co/M9LrkW7Qww ●바로 옆 폼페이오에 \"북한 간 줄\"…이르면 주말 3차 방북 ●붉은불개미, 불길한 '공주개미'…대량 번식 가능성은? ●73년 만에 용… https://t.co/Tezu5855hr",
        "name": "JTBC_news",
        "num_likes": 15,
        "num_shares": 16,
        "post_id": "1010143588980699137"
    },
    {
        "created_time": "2018-06-22 21:26:37",
        "message": "[JTBC 뉴스룸] 서울, 올 들어 가장 더워. 경기도 광주 35.7도, 강원·경상 내륙 폭염주의보. 주말까지 불볕 더위 계속. https://t.co/EqpSezqPRZ https://t.co/GOLlu92lzN",
        "name": "JTBC_news",
        "num_likes": 18,
        "num_shares": 96,
        "post_id": "1010136976568168448"
    },
    {
        "created_time": "2018-06-22 21:24:58",
        "message": "[JTBC 뉴스룸] 대구·부산 수돗물 '환경호르몬' 검출 논란. 물을 끓이거나 정수기로 걸러도 없앨 수 없는 물질. 마트마다 생수가 동 나고 시민들 불안 계속. https://t.co/I46lGeN3Bd https://t.co/o43eKScWIe",
        "name": "JTBC_news",
        "num_likes": 50,
        "num_shares": 204,
        "post_id": "1010136562661613568"
    },
    {
        "created_time": "2018-06-22 21:22:50",
        "message": "[JTBC 뉴스룸] '강진 여고생' 실종 일주일째. 논둑, 마을 빈집, 저수지까지 구석구석 수색. 골든타임 '일주일' 지나면 사건 장기화 우려도. https://t.co/HClaXhiDO2 https://t.co/LFYBUAc6Go",
        "name": "JTBC_news",
        "num_likes": 26,
        "num_shares": 54,
        "post_id": "1010136023639003141"
    },
    {
        "created_time": "2018-06-22 21:21:34",
        "message": "[JTBC 뉴스룸] 울산~포항 고속도로 터널서 달리던 차량 화재. 불이 나자마자 검은 연기로 가득. 25명은 구조됐고 3명은 연기 마셔 치료. https://t.co/Ocfwvpau1i https://t.co/amlvVMqcGC",
        "name": "JTBC_news",
        "num_likes": 18,
        "num_shares": 22,
        "post_id": "1010135706079920129"
    },
    {
        "created_time": "2018-06-22 20:51:51",
        "message": "[JTBC 뉴스룸] 평택항 이어 부산항에서도 붉은불개미 3000마리 발견. 번식 가능한 '공주개미' 11마리도 첫 관찰. 확산은 시간 문제. https://t.co/Js4OPE3IZX https://t.co/NqZd4NRz6O",
        "name": "JTBC_news",
        "num_likes": 41,
        "num_shares": 269,
        "post_id": "1010128226214002688"
    },
    {
        "created_time": "2018-06-22 20:50:22",
        "message": "[JTBC 뉴스룸] 푸틴과 정상회담 '남·북·러 협력 논의' 주목. 문 대통령은 멕시코전 관람 후 일요일 귀국. https://t.co/tEtFlJeXM1 https://t.co/WXDxjPUd2Q",
        "name": "JTBC_news",
        "num_likes": 24,
        "num_shares": 27,
        "post_id": "1010127854258962432"
    },
    {
        "created_time": "2018-06-22 20:48:23",
        "message": "[JTBC 뉴스룸] 부동산 안정 '마지막 카드' 종부세 강화 시동. 가장 눈길을 끄는 건 다주택자에 더 걷는 '차등 과세' 방안. 세수 최대 1조3000억원 더 걷힐 듯.… https://t.co/iX3RVuMdRB",
        "name": "JTBC_news",
        "num_likes": 27,
        "num_shares": 29,
        "post_id": "1010127354369228800"
    },
    {
        "created_time": "2018-06-22 20:23:34",
        "message": "[JTBC 뉴스룸] 김정은 위원장 팔짱 낀 이설주 '눈길'. 북한 '3차 방중' 기록영화 공개. 평상복을 입은 노광철 인민무력상도 포착. https://t.co/XWnhefiRiy https://t.co/vO7A13Y6xR",
        "name": "JTBC_news",
        "num_likes": 22,
        "num_shares": 20,
        "post_id": "1010121112280133632"
    },
    {
        "created_time": "2018-06-22 20:20:28",
        "message": "[JTBC 뉴스룸] '속도전' 강조한 트럼프 \"북 전면적 비핵화 이미 시작\". 또 미군유해송환팀이 북한에 들어가 송환 절차에 착수한 것으로 알려져. https://t.co/uXVDNrwePR https://t.co/h3OD3fFo00",
        "name": "JTBC_news",
        "num_likes": 29,
        "num_shares": 38,
        "post_id": "1010120331992825856"
    },
    {
        "created_time": "2018-06-22 20:18:33",
        "message": "[JTBC 뉴스룸] '이산가족 상봉' 8월 20일부터 1주일간 금강산서 열기로 합의. 대상은 남북 각각 100명씩. 8월 4일 최종명단 교환. https://t.co/CfvGu55I8R https://t.co/0fJq06AnoJ",
        "name": "JTBC_news",
        "num_likes": 54,
        "num_shares": 82,
        "post_id": "1010119846653120512"
    },
    {
        "created_time": "2018-06-22 19:46:03",
        "message": "[JTBC 뉴스룸] JTBC 온에어 ▶https://t.co/M9LrkW7Qww  네이버ㆍ다음ㆍ네이트ㆍ유튜브를 통해 실시간 시청 가능합니다. https://t.co/o4Za4niEbv",
        "name": "JTBC_news",
        "num_likes": 8,
        "num_shares": 3,
        "post_id": "1010111670922801152"
    },
    {
        "created_time": "2018-06-22 19:45:33",
        "message": "[JTBC 뉴스룸] 6월 22일 주요뉴스 ● 이산가족 상봉, 금강산서 8월 20~26일 ● 종부세 강화안…다주택 세금 최대 38%↑ ● 트럼프 \"북 전면적 비핵화 이미 시작\" ● 부산항 붉은불개미…'공주개미' 공포 ● 대구·부산 수돗물서 '환경호르몬'",
        "name": "JTBC_news",
        "num_likes": 17,
        "num_shares": 17,
        "post_id": "1010111544460374018"
    },
    {
        "created_time": "2018-06-22 19:23:16",
        "message": "[속보] 남북, 이산가족 상봉 8월 20일~26일 금강산 개최 합의",
        "name": "JTBC_news",
        "num_likes": 832,
        "num_shares": 3502,
        "post_id": "1010105934599806976"
    },
    {
        "created_time": "2018-06-22 16:12:54",
        "message": "대법원 \"휴일근무는 연장근무 아니다\"...성남시 환경미화원 임금청구 소송에서 10년 만에 패소. 근로기준법 개정안이 근거로 작용. https://t.co/NHzTYKdzW8 https://t.co/2ftfimlrS5",
        "name": "JTBC_news",
        "num_likes": 23,
        "num_shares": 88,
        "post_id": "1010058026256961537"
    },
    {
        "created_time": "2018-06-22 14:14:04",
        "message": "전남 장성군서 6번째 싱크홀, 폭은 좁지만 더 깊어 트랙터 빠지기도…해당 군청은 원인 파악에 나섰지만, 반복되는 지반 침하에 주민 불안 가중. https://t.co/OsNXEMXOEj https://t.co/fLuVZ80ajv",
        "name": "JTBC_news",
        "num_likes": 23,
        "num_shares": 94,
        "post_id": "1010028122450771971"
    },
    {
        "created_time": "2018-06-22 14:13:42",
        "message": "'검경 수사권 조정안' 발표됐지만...국회 법 개정 과정에 난항 예상. 여야 간 협의가 장기화될 경우 조정안 취지가 흐려질 것이라는 우려도. https://t.co/YxeaqMg5MW https://t.co/uFAzRo2IPO",
        "name": "JTBC_news",
        "num_likes": 11,
        "num_shares": 26,
        "post_id": "1010028031975407618"
    },
    {
        "created_time": "2018-06-22 11:19:40",
        "message": "울산서 정체 불명의 '가스 냄새' 신고 잇따라. 해마다 반복되는 현상에 주민 불안감 커지고 있지만, 긴급 조사에서도 원인은 밝혀지지 않아. https://t.co/m66vbQLGCd https://t.co/bHzO4rk90W",
        "name": "JTBC_news",
        "num_likes": 41,
        "num_shares": 427,
        "post_id": "1009984234579099648"
    },
    {
        "created_time": "2018-06-22 10:18:07",
        "message": "수거는 언제?…1만여 가구 '라돈침대와 동거' 여전히. 당초 이번 주까지 수거 완료 예정이었으나 남은 수거대상 1만 여개 이상. https://t.co/1jLqJZTmbY https://t.co/TjYHnkUlgl",
        "name": "JTBC_news",
        "num_likes": 17,
        "num_shares": 33,
        "post_id": "1009968744561459200"
    },
    {
        "created_time": "2018-06-22 09:52:52",
        "message": "#날씨 전국 33도 안팎까지 무더위 기승. 수도권 미세먼지 농도↑중서부 오전 중 '나쁨'. 낮 기온은 서울 31도, 광주 32도, 대구 33도까지 오를 전망. https://t.co/3F2foPIDYo https://t.co/PHAUbWrM6e",
        "name": "JTBC_news",
        "num_likes": 22,
        "num_shares": 90,
        "post_id": "1009962390975275008"
    },
    {
        "created_time": "2018-06-22 09:26:02",
        "message": "오늘(22일) 오전 10시, 북측 금강산호텔에서 남북 적십자회담 개최. 이산가족·친척 상봉 등 인도적 문제 논의 예정. https://t.co/G7Wnscy3nF https://t.co/SumtL6Ud92",
        "name": "JTBC_news",
        "num_likes": 25,
        "num_shares": 52,
        "post_id": "1009955636581289990"
    },
    {
        "created_time": "2018-06-22 08:58:35",
        "message": "문 대통령, 러시아 하원 연설서 '남·북·러 3각 경제협력' 강조. 가스, 철도 등 9개 중점 분야를 협력하는 '극동개발협력' 등 계획 밝혀. https://t.co/Jg7LgkXlaW https://t.co/tmE6rGILbP",
        "name": "JTBC_news",
        "num_likes": 44,
        "num_shares": 36,
        "post_id": "1009948727631441921"
    },
    {
        "created_time": "2018-06-22 06:47:27",
        "message": "6월 22일 JTBC 아침&amp; 예고 ●사상 첫 하원 연설…오늘 정상회담 ●금강산서 이산상봉 논의…새벽 통보 ●검·경 불만?…국민 입장서 접근해야 ●'쇄신 의원총회'…계파 갈등만 확인 https://t.co/ZWV9veSpdU",
        "name": "JTBC_news",
        "num_likes": 20,
        "num_shares": 10,
        "post_id": "1009915727481004032"
    }
]